iotrelay.py
iotrelay-1.2.3.dist-info/DESCRIPTION.rst
iotrelay-1.2.3.dist-info/METADATA
iotrelay-1.2.3.dist-info/RECORD
iotrelay-1.2.3.dist-info/WHEEL
iotrelay-1.2.3.dist-info/entry_points.txt
iotrelay-1.2.3.dist-info/metadata.json
iotrelay-1.2.3.dist-info/top_level.txt
