Metadata-Version: 2.0
Name: iotrelay
Version: 1.2.3
Summary: IoT Relay - Relay data between data sources and destinations.
Home-page: http://iot-relay.readthedocs.org
Author: Emmanuel Levijarvi
Author-email: emansl@gmail.com
License: BSD
Keywords: IoT relay time series
Platform: UNKNOWN
Classifier: Development Status :: 4 - Beta
Classifier: Intended Audience :: Developers
Classifier: Topic :: Home Automation
Classifier: Topic :: Utilities
Classifier: License :: OSI Approved :: BSD License
Classifier: Operating System :: OS Independent
Classifier: Programming Language :: Python :: 2.7
Classifier: Programming Language :: Python :: 3
